[
  {
    "id": "1",
    "name": "Implementação de Sistema",
    "description": "Implementação do novo sistema de gestão documental",
    "stages": [
      {
        "id": "1-1",
        "name": "Análise de Requisitos",
        "status": "completed",
        "deadline": "2023-03-15",
        "responsible": "Ana Silva",
        "description": "Coletar e documentar todos os requisitos do sistema"
      },
      {
        "id": "1-2",
        "name": "Desenvolvimento",
        "status": "in-progress",
        "deadline": "2023-04-30",
        "responsible": "Carlos Oliveira"
      }
    ],
    "members": 5,
    "color": "#0A4338",
    "createdAt": "2023-01-10",
    "updatedAt": "2023-02-20"
  },
  {
    "id": "2",
    "name": "Migração de Documentos",
    "description": "Digitalização e migração do arquivo físico para digital",
    "stages": [
      {
        "id": "2-1",
        "name": "Inventário Documental",
        "status": "completed",
        "deadline": "2023-02-10",
        "responsible": "Pedro Alves"
      }
    ],
    "members": 4,
    "color": "#062E29",
    "createdAt": "2023-01-15",
    "updatedAt": "2023-02-25"
  }
]
